helloassotestchapterpython/__init__.py
helloassotestchapterpython/utils.py
hello_asso_test_chapter_python-0.1.0.dist-info/METADATA
hello_asso_test_chapter_python-0.1.0.dist-info/WHEEL
hello_asso_test_chapter_python-0.1.0.dist-info/RECORD
